infrablue/__init__.py
infrablue/apps.py
infrablue/asgi.py
infrablue/bigbluebutton.py
infrablue/forms.py
infrablue/menus.py
infrablue/migrations/0001_initial.py
infrablue/migrations/__init__.py
infrablue/mixins.py
infrablue/models.py
infrablue/preferences.py
infrablue/registries.py
infrablue/settings.py
infrablue/signals.py
infrablue/static/img/infrablue-banner.svg
infrablue/static/img/infrablue-icon.svg
infrablue/static/js/main.js
infrablue/static/materialize.scss
infrablue/static/style.scss
infrablue/static/theme.scss
infrablue/templates/components/save_button.html
infrablue/templates/django_registration/activation_complete.html
infrablue/templates/django_registration/activation_email_body.txt
infrablue/templates/django_registration/activation_email_subject.txt
infrablue/templates/django_registration/activation_failed.html
infrablue/templates/django_registration/registration_closed.html
infrablue/templates/django_registration/registration_complete.html
infrablue/templates/django_registration/registration_disallowed.html
infrablue/templates/django_registration/registration_form.html
infrablue/templates/dynamic_preferences/form.html
infrablue/templates/dynamic_preferences/sections.html
infrablue/templates/infrablue/base.html
infrablue/templates/infrablue/base_module.html
infrablue/templates/infrablue/group_delete.html
infrablue/templates/infrablue/group_detail.html
infrablue/templates/infrablue/group_list.html
infrablue/templates/infrablue/group_update.html
infrablue/templates/infrablue/index.html
infrablue/templates/infrablue/meeting_delete.html
infrablue/templates/infrablue/meeting_detail.html
infrablue/templates/infrablue/meeting_join.html
infrablue/templates/infrablue/meeting_list.html
infrablue/templates/infrablue/meeting_update.html
infrablue/templates/infrablue/meeting_url_delete.html
infrablue/templates/infrablue/menu.html
infrablue/templates/infrablue/property_card.html
infrablue/templates/infrablue/server_group_delete.html
infrablue-0.1.0a1.dist-info/WHEEL
infrablue-0.1.0a1.dist-info/METADATA
infrablue-0.1.0a1.dist-info/RECORD
