Metadata-Version: 2.1
Name: infrablue
Version: 0.1.0a1
Summary: Material design frontend and server manager for BigBlueButton
Home-page: https://edugit.org/nik/infrablue
Author: Dominik George
Author-email: dominik.george@teckids.org
Requires-Python: >=3.6,<4.0
Classifier: Programming Language :: Python :: 3
Classifier: Programming Language :: Python :: 3.6
Classifier: Programming Language :: Python :: 3.7
Classifier: Programming Language :: Python :: 3.8
Provides-Extra: ldap
Provides-Extra: social
Requires-Dist: Django (<3.2)
Requires-Dist: bigbluebutton2[django,sysstat] (>=0.1a8,<0.2)
Requires-Dist: colour (>=0.1.5,<0.2.0)
Requires-Dist: django-auth-ldap (>=2.1.1,<3.0.0); extra == "ldap"
Requires-Dist: django-dynamic-preferences (>=1.9,<2.0)
Requires-Dist: django-guardian (>=2.3.0,<3.0.0)
Requires-Dist: django-material (>=1.6.3,<2.0.0)
Requires-Dist: django-registration (>=3.1,<4.0)
Requires-Dist: django-two-factor-auth[yubikey,phonenumbers,call,sms] (>=1.11.0,<2.0.0)
Requires-Dist: django-yarnpkg (>=6.0.1,<7.0.0)
Requires-Dist: django_any_js (>=1.0.3,<2.0.0)
Requires-Dist: django_favicon_plus_reloaded (>=1.0.4,<2.0.0)
Requires-Dist: django_menu_generator (>=1.0.4,<2.0.0)
Requires-Dist: django_sass_processor (>=0.8,<0.9)
Requires-Dist: dynaconf (>=2.2.3,<3.0.0)
Requires-Dist: libsass (>=0.20.0,<0.21.0)
Requires-Dist: psycopg2 (>=2.8.5,<3.0.0)
Requires-Dist: python-memcached (>=1.59,<2.0)
Requires-Dist: social-auth-app-django (>=4.0.0,<5.0.0); extra == "social"
Project-URL: Repository, https://edugit.org/nik/infrablue
